[
  {
    "layout": "token_def",
    "name": "Treasure Token",
    "token": "A colorless Treasure artifact with \"{T}, Sacrifice this token: Add one mana of any color.\""
  },
  {
    "layout": "token_def",
    "name": "Food Token",
    "token": "A colorless Food artifact with \"{2}, {T}, Sacrifice this token: You gain 3 life.\""
  },
  {
    "layout": "token_def",
    "name": "Gold Token",
    "token": "A colorless Gold artifact with \"Sacrifice this token: Add one mana of any color.\""
  },
  {
    "layout": "token_def",
    "name": "Walker Token",
    "token": "A 2/2 black Zombie creature named Walker."
  },
  {
    "layout": "token_def",
    "name": "Shard Token",
    "token": "A colorless Shard enchantment with \"{2}, Sacrifice this token: Scry 1, then draw a card.\""
  },
  {
    "layout": "token_def",
    "name": "Clue Token",
    "token": "A colorless Clue artifact with \"{2}, Sacrifice this token: Draw a card.\""
  },
  {
    "layout": "token_def",
    "name": "Blood Token",
    "token": "A colorless Blood artifact with \"{1}, {T}, Discard a card, Sacrifice this token: Draw a card.\""
  },
  {
    "layout": "token_def",
    "name": "Powerstone Token",
    "token": "A colorless Powerstone artifact with \"{T}: Add {C}. This mana can't be spent to cast a nonartifact spell.\""
  },
  {
    "layout": "token_def",
    "name": "Incubator Token",
    "token": "A double-faced token.\nIts front face is a colorless Incubator artifact with \"{2}: Transform this token.\"\nIts back face is a 0/0 colorless Phyrexian artifact creature."
  },
  {
    "layout": "token_def",
    "name": "Cursed Role Token",
    "token": "A colorless Aura Role enchantment named Cursed with enchant creature and \"Enchanted creature has base power and toughness 1/1.\""
  },
  {
    "layout": "token_def",
    "name": "Monster Role Token",
    "token": "A colorless Aura Role enchantment named Monster with enchant creature and \"Enchanted creature gets +1/+1 and has trample.\""
  },
  {
    "layout": "token_def",
    "name": "Royal Role Token",
    "token": "A colorless Aura Role enchantment named Royal with enchant creature and \"Enchanted creature gets +1/+1 and has ward {1}.\""
  },
  {
    "layout": "token_def",
    "name": "Sorcerer Role Token",
    "token": "A colorless Aura Role enchantment named Sorcerer with enchant creature and \"Enchanted creature gets +1/+1 and has 'Whenever this creature attacks, scry 1.'\""
  },
  {
    "layout": "token_def",
    "name": "Virtuous Role Token",
    "token": "A colorless Aura Role enchantment named Virtuous with enchant creature and \"Enchanted creature gets +1/+1 for each enchantment you control.\""
  },
  {
    "layout": "token_def",
    "name": "Wicked Role Token",
    "token": "A colorless Aura Role enchantment named Wicked with enchant creature, \"Enchanted creature gets +1/+1,\" and \"When this token is put into a graveyard from the battlefield, each opponent loses 1 life.\""
  },
  {
    "layout": "token_def",
    "name": "Young Hero Role Token",
    "token": "A colorless Aura Role enchantment named Young Hero with enchant creature and \"Enchanted creature has 'Whenever this creature attacks, if its toughness is 3 or less, put a +1/+1 counter on it.'\""
  },
  {
    "layout": "token_def",
    "name": "Map Token",
    "token": "A colorless Map artifact with \"{1}, {T}, Sacrifice this token: Target creature you control explores. Activate only as a sorcery.\""
  },
  {
    "layout": "token_def",
    "name": "Junk Token",
    "token": "A colorless Junk artifact with \"{T}, Sacrifice this token: Exile the top card of your library. You may play that card this turn. Activate only as a sorcery.\""
  },
  {
    "layout": "token_def",
    "name": "Lander Token",
    "token": "A colorless Lander artifact with \"{2}, {T}, Sacrifice this token: Search your library for a basic land card, put it onto the battlefield tapped, then shuffle.\""
  },
  {
    "layout": "token_def",
    "name": "Mutagen Token",
    "token": "A colorless Mutagen artifact with \"{1}, {T}, Sacrifice this token: Put a +1/+1 counter on target creature. Activate only as a sorcery.\""
  },
  {
    "layout": "token_def",
    "name": "Vibranium Token",
    "token": "A colorless Vibranium artifact with indestructible and \"{T}: Add {C}. This mana can't be spent to cast a nonartifact spell.\""
  },
  {
    "layout": "token_def",
    "name": "Fish Token",
    "token": "A 1/1 blue Fish creature."
  },
  {
    "layout": "token_def",
    "name": "Octopus Token",
    "token": "A 1/1 blue Octopus creature."
  }
]
